[{"name": "id_no", "pose": "Unspecified", "truncated": 0, "difficult": 0, "bndbox": {"xmin": 153, "ymin": 14, "xmax": 250, "ymax": 19}}, {"name": "surname", "pose": "Unspecified", "truncated": 0, "difficult": 0, "bndbox": {"xmin": 145, "ymin": 50, "xmax": 170, "ymax": 64}}, {"name": "forenames", "pose": "Unspecified", "truncated": 0, "difficult": 0, "bndbox": {"xmin": 143, "ymin": 72, "xmax": 184, "ymax": 84}}, {"name": "country_of_birth", "pose": "Unspecified", "truncated": 0, "difficult": 0, "bndbox": {"xmin": 145, "ymin": 102, "xmax": 203, "ymax": 111}}, {"name": "date_of_birth", "pose": "Unspecified", "truncated": 0, "difficult": 0, "bndbox": {"xmin": 206, "ymin": 110, "xmax": 256, "ymax": 120}}, {"name": "date_issued", "pose": "Unspecified", "truncated": 0, "difficult": 0, "bndbox": {"xmin": 207, "ymin": 134, "xmax": 260, "ymax": 145}}]